{
    "_id": "6RddnB4LpMmMv54kN",
    "url": "/%2F-EMv7UAPfe4R3YThfIf5IA_-74.250923_40.511643_0_54.94.jpg",
    "socName": "Cityscapes",
    "firstEditDate": "2020-05-02T15:15:23.128Z",
    "lastEditDate": "2020-05-06T05:24:21.242Z",
    "folder": "",
    "objects": [
        {
            "classIndex": 1,
            "layer": 0,
            "polygon": [
                {
                    "x": 483.52529258148763,
                    "y": 462.6149530902409
                },
                {
                    "x": 504.57181545604027,
                    "y": 462.6149530902409
                },
                {
                    "x": 508.28590772802016,
                    "y": 567.8475674630042
                },
                {
                    "x": 484.76332333881425,
                    "y": 564.1334751910243
                }
            ],
            "label": "trunk"
        },
        {
            "classIndex": 1,
            "layer": 0,
            "polygon": [
                {
                    "x": 958.9291033949124,
                    "y": 457.66283006093437
                },
                {
                    "x": 958.9291033949124,
                    "y": 434.14024567172845
                },
                {
                    "x": 994.8319953573846,
                    "y": 437.8543379437083
                },
                {
                    "x": 983.689718541445,
                    "y": 500.99390656736637
                },
                {
                    "x": 988.6418415707515,
                    "y": 546.8010445884515
                },
                {
                    "x": 953.976980365606,
                    "y": 534.4207370151853
                }
            ],
            "label": "trunk"
        }
    ],
    "tags": [],
    "file": "-EMv7UAPfe4R3YThfIf5IA_-74.250923_40.511643_0_54.94.jpg"
}