{
    "_id": "A8oHu9bYRXXkmxo6j",
    "url": "/%2F0BafuBo9OVLeUBSaxSol2g_-74.240878_40.517547_0_142.22.jpg",
    "socName": "Cityscapes",
    "firstEditDate": "2020-05-03T03:01:04.515Z",
    "lastEditDate": "2020-05-06T05:43:15.986Z",
    "folder": "",
    "objects": [
        {
            "classIndex": 1,
            "layer": 0,
            "polygon": [
                {
                    "x": 295.22537034529455,
                    "y": 445.11454647451404
                },
                {
                    "x": 298.06511577522,
                    "y": 406.57514421123904
                },
                {
                    "x": 312.2638429248477,
                    "y": 417.5284480123804
                },
                {
                    "x": 306.17867414643587,
                    "y": 444.30319063739245
                },
                {
                    "x": 307.3957079021182,
                    "y": 495.82428629461265
                },
                {
                    "x": 294.41401450817295,
                    "y": 491.7675071090048
                }
            ],
            "label": "trunk"
        },
        {
            "classIndex": 1,
            "layer": 0,
            "polygon": [
                {
                    "x": 710.9485714285713,
                    "y": 462.0662578585937
                },
                {
                    "x": 715.5124480123802,
                    "y": 425.0481477899217
                },
                {
                    "x": 722.1047141889933,
                    "y": 426.5694399845247
                },
                {
                    "x": 723.6260063835961,
                    "y": 465.6159396460006
                },
                {
                    "x": 721.5976167907924,
                    "y": 491.98500435245194
                },
                {
                    "x": 724.1331037817972,
                    "y": 524.946335235516
                },
                {
                    "x": 711.9627662249735,
                    "y": 522.9179456427121
                }
            ],
            "label": "trunk"
        },
        {
            "classIndex": 1,
            "layer": 0,
            "polygon": [
                {
                    "x": 884.8057258922528,
                    "y": 472.20226327497835
                },
                {
                    "x": 879.1008801624915,
                    "y": 448.74900860818263
                },
                {
                    "x": 896.2154173517748,
                    "y": 444.94577812167523
                },
                {
                    "x": 896.2154173517748,
                    "y": 465.22967404971473
                },
                {
                    "x": 903.8218783247897,
                    "y": 476.6393655092369
                },
                {
                    "x": 898.7509043427799,
                    "y": 490.58454395976406
                },
                {
                    "x": 901.2863913337848,
                    "y": 536.2233097978528
                },
                {
                    "x": 886.7073411355063,
                    "y": 534.9555663023503
                }
            ],
            "label": "trunk"
        }
    ],
    "tags": [],
    "file": "0BafuBo9OVLeUBSaxSol2g_-74.240878_40.517547_0_142.22.jpg"
}