{
    "_id": "MoHM8EnQ95D6XLMiM",
    "url": "/%2F0SJgOPjKNCRvIFPQPYfV-Q_-74.209251_40.54912_0_344.94.jpg",
    "socName": "Cityscapes",
    "objects": [
        {
            "classIndex": 1,
            "layer": 0,
            "polygon": [
                {
                    "x": 132.61785472482836,
                    "y": 408.94384369861694
                },
                {
                    "x": 145.9291614276043,
                    "y": 411.47933068962186
                },
                {
                    "x": 144.6614179321018,
                    "y": 483.7407099332625
                },
                {
                    "x": 131.98398297707715,
                    "y": 483.1068381855112
                },
                {
                    "x": 133.2517264725796,
                    "y": 478.66973595125256
                }
            ],
            "label": "trunk"
        },
        {
            "classIndex": 1,
            "layer": 0,
            "polygon": [
                {
                    "x": 597.8797175742336,
                    "y": 501.4891188702969
                },
                {
                    "x": 603.5845633039946,
                    "y": 417.18417641938294
                },
                {
                    "x": 620.6991004932779,
                    "y": 417.8180481671341
                },
                {
                    "x": 620.6991004932779,
                    "y": 417.8180481671341
                },
                {
                    "x": 616.8958700067705,
                    "y": 501.4891188702969
                },
                {
                    "x": 597.8797175742336,
                    "y": 501.4891188702969
                }
            ],
            "label": "trunk"
        },
        {
            "classIndex": 1,
            "layer": 0,
            "polygon": [
                {
                    "x": 907.6805725892253,
                    "y": 413.80088596576076
                },
                {
                    "x": 931.0070529064707,
                    "y": 420.90024954057463
                },
                {
                    "x": 920.865104942451,
                    "y": 500.00744365992847
                },
                {
                    "x": 896.5244298288037,
                    "y": 495.44356707611956
                }
            ],
            "label": "trunk"
        }
    ],
    "tags": [],
    "folder": "",
    "file": "0SJgOPjKNCRvIFPQPYfV-Q_-74.209251_40.54912_0_344.94.jpg",
    "lastEditDate": "2020-05-06T05:08:20.299Z",
    "firstEditDate": "2020-05-06T05:08:20.299Z"
}