{
    "_id": "FmrFNYWQsY2CPigtB",
    "url": "/%2F0umLmIveCOGfTkff0AZRgw_-74.216545_40.54943_0_165.52.jpg",
    "socName": "Cityscapes",
    "objects": [
        {
            "classIndex": 1,
            "layer": 0,
            "polygon": [
                {
                    "x": 164.47704110649025,
                    "y": 503.8700996227878
                },
                {
                    "x": 165.69407486217264,
                    "y": 453.1603598026891
                },
                {
                    "x": 165.69407486217264,
                    "y": 409.7528225166846
                },
                {
                    "x": 166.91110861785498,
                    "y": 376.8929111132606
                },
                {
                    "x": 171.37356572202367,
                    "y": 348.90113473256616
                },
                {
                    "x": 190.03474997581998,
                    "y": 360.665794370829
                },
                {
                    "x": 190.84610581294157,
                    "y": 367.56231898636247
                },
                {
                    "x": 185.1666149530905,
                    "y": 375.67587735757826
                },
                {
                    "x": 184.3552591159689,
                    "y": 396.7711291227393
                },
                {
                    "x": 180.29847993036103,
                    "y": 410.56417835380626
                },
                {
                    "x": 180.70415784892182,
                    "y": 479.9351024277012
                },
                {
                    "x": 183.94958119740815,
                    "y": 506.3041671341524
                },
                {
                    "x": 187.19500454589442,
                    "y": 510.7666242383212
                },
                {
                    "x": 161.63729567656472,
                    "y": 516.4461150981722
                }
            ],
            "label": "trunk"
        },
        {
            "classIndex": 1,
            "layer": 0,
            "polygon": [
                {
                    "x": 603.7648205822613,
                    "y": 419.65825708482447
                },
                {
                    "x": 599.7080413966535,
                    "y": 383.65434181255443
                },
                {
                    "x": 591.0873856272368,
                    "y": 354.24269271689724
                },
                {
                    "x": 603.7648205822613,
                    "y": 351.2001083276913
                },
                {
                    "x": 615.935158139085,
                    "y": 385.68273140535837
                },
                {
                    "x": 624.0487165103008,
                    "y": 394.8104845729762
                },
                {
                    "x": 624.0487165103008,
                    "y": 411.54469871360874
                },
                {
                    "x": 628.6125930941097,
                    "y": 420.1653544830255
                },
                {
                    "x": 623.5416191120999,
                    "y": 428.7860102524422
                },
                {
                    "x": 621.5132295192958,
                    "y": 457.1834645516975
                },
                {
                    "x": 602.2435283876584,
                    "y": 454.14088016249156
                }
            ],
            "label": "trunk"
        },
        {
            "classIndex": 1,
            "layer": 0,
            "polygon": [
                {
                    "x": 513.4292223232422,
                    "y": 375.95127878518247
                },
                {
                    "x": 514.9870255305157,
                    "y": 333.371324453042
                },
                {
                    "x": 522.7760415668829,
                    "y": 335.4483953960733
                },
                {
                    "x": 522.5164076990039,
                    "y": 367.6429950130575
                },
                {
                    "x": 523.5549431705197,
                    "y": 382.9613932179129
                },
                {
                    "x": 515.7659271341524,
                    "y": 380.62468840700274
                },
                {
                    "x": 511.35215138021096,
                    "y": 379.3265190676082
                }
            ],
            "label": "trunk"
        }
    ],
    "tags": [],
    "folder": "",
    "file": "0umLmIveCOGfTkff0AZRgw_-74.216545_40.54943_0_165.52.jpg",
    "lastEditDate": "2020-05-05T23:29:42.456Z",
    "firstEditDate": "2020-05-05T23:29:42.456Z"
}