{
    "_id": "9976pMnNzJsqPtWDf",
    "url": "/%2Fa%2F2722NdlQoSKUoJ9EQaYRrA_-74.239362_40.508919_0_254.95.jpg",
    "socName": "Cityscapes",
    "objects": [
        {
            "classIndex": 1,
            "layer": 0,
            "polygon": [
                {
                    "x": 355.86429221370076,
                    "y": 513.8502014818666
                },
                {
                    "x": 362.8923956843884,
                    "y": 467.20915117639413
                },
                {
                    "x": 369.9204991550761,
                    "y": 439.09673729364357
                },
                {
                    "x": 398.03291303782663,
                    "y": 444.8470037696608
                },
                {
                    "x": 395.47723904848567,
                    "y": 460.18104770570653
                },
                {
                    "x": 388.449135577798,
                    "y": 464.01455868971794
                },
                {
                    "x": 381.42103210711036,
                    "y": 490.84913557779805
                },
                {
                    "x": 378.86535811776946,
                    "y": 526.6285714285715
                },
                {
                    "x": 381.42103210711036,
                    "y": 562.4080072793449
                },
                {
                    "x": 359.05888470037695,
                    "y": 564.963681268686
                },
                {
                    "x": 354.58645521903026,
                    "y": 557.9355777979982
                }
            ],
            "label": "trunk"
        }
    ],
    "tags": [],
    "folder": "/a",
    "file": "2722NdlQoSKUoJ9EQaYRrA_-74.239362_40.508919_0_254.95.jpg",
    "lastEditDate": "2020-05-20T02:45:42.038Z",
    "firstEditDate": "2020-05-20T02:45:42.038Z"
}