{
    "_id": "7e6rzZrWvTQLbt2gj",
    "url": "/%2F2lVS3yzJNK_k9tqer-CxBA_-74.205814_40.539322_0_342.30.jpg",
    "socName": "Cityscapes",
    "objects": [
        {
            "classIndex": 1,
            "layer": 0,
            "polygon": [
                {
                    "x": 20.50178934132895,
                    "y": 496.0417835380598
                },
                {
                    "x": 47.738466002514755,
                    "y": 486.13753747944685
                },
                {
                    "x": 55.166650546474514,
                    "y": 476.2332914208338
                },
                {
                    "x": 47.738466002514755,
                    "y": 447.75858400232136
                },
                {
                    "x": 40.31028145855499,
                    "y": 401.95144598123613
                },
                {
                    "x": 34.12012767192186,
                    "y": 342.52596962955806
                },
                {
                    "x": 30.40603539994197,
                    "y": 274.43427797659353
                },
                {
                    "x": 0,
                    "y": 268.24412418996036
                },
                {
                    "x": 0,
                    "y": 493.5657220234066
                },
                {
                    "x": 0.6932972241029142,
                    "y": 497.2798142953864
                }
            ],
            "label": "trunk"
        },
        {
            "classIndex": 1,
            "layer": 0,
            "polygon": [
                {
                    "x": 845.0302737208629,
                    "y": 457.66283006093437
                },
                {
                    "x": 856.1725505368024,
                    "y": 455.18676854628114
                },
                {
                    "x": 866.0767965954153,
                    "y": 549.2771061031049
                },
                {
                    "x": 856.1725505368024,
                    "y": 552.9911983750847
                }
            ],
            "label": "trunk"
        }
    ],
    "tags": [],
    "folder": "",
    "file": "2lVS3yzJNK_k9tqer-CxBA_-74.205814_40.539322_0_342.30.jpg",
    "lastEditDate": "2020-05-06T00:29:47.055Z",
    "firstEditDate": "2020-05-06T00:29:47.055Z"
}