{
    "_id": "KT5ARthj6ZtZz9BMW",
    "url": "/%2F3VnEfosnqw7SesBOTLY0tw_-74.235099_40.521264_0_275.66.jpg",
    "socName": "Cityscapes",
    "objects": [
        {
            "classIndex": 1,
            "layer": 0,
            "polygon": [
                {
                    "x": 487.11577986265576,
                    "y": 403.23147074185135
                },
                {
                    "x": 491.1725590482636,
                    "y": 402.4201149047298
                },
                {
                    "x": 488.7384915368989,
                    "y": 425.9494341812556
                },
                {
                    "x": 486.30442402553416,
                    "y": 424.3267225070125
                }
            ],
            "label": "trunk"
        },
        {
            "classIndex": 1,
            "layer": 0,
            "polygon": [
                {
                    "x": 336.4860695943517,
                    "y": 421.1205199729181
                },
                {
                    "x": 337.94001925447355,
                    "y": 408.24268012612436
                },
                {
                    "x": 338.7708476316861,
                    "y": 410.11204397485244
                },
                {
                    "x": 337.3168979715642,
                    "y": 426.72861151910246
                },
                {
                    "x": 333.9935844627142,
                    "y": 425.69007604758684
                }
            ],
            "label": "trunk"
        }
    ],
    "tags": [],
    "folder": "",
    "file": "3VnEfosnqw7SesBOTLY0tw_-74.235099_40.521264_0_275.66.jpg",
    "lastEditDate": "2020-05-05T22:45:44.696Z",
    "firstEditDate": "2020-05-05T22:45:44.696Z"
}