{
    "_id": "6x75xL6DyR8dTFnMQ",
    "url": "/%2Fa%2F68XYU5MDzePhXHI1muH_qg_-74.217122_40.544782_0_164.64.jpg",
    "socName": "Cityscapes",
    "objects": [
        {
            "classIndex": 1,
            "layer": 0,
            "polygon": [
                {
                    "x": 392.09678517093516,
                    "y": 512.7876959937608
                },
                {
                    "x": 393.7324165241134,
                    "y": 461.10174523332927
                },
                {
                    "x": 388.1712699233075,
                    "y": 424.7907291927729
                },
                {
                    "x": 388.1712699233075,
                    "y": 400.910511436371
                },
                {
                    "x": 422.1924020694143,
                    "y": 402.5461427895492
                },
                {
                    "x": 414.01424530352324,
                    "y": 420.5380876745095
                },
                {
                    "x": 413.35999276225186,
                    "y": 438.20290628883424
                },
                {
                    "x": 417.28550800987966,
                    "y": 523.582862924737
                },
                {
                    "x": 416.95838173924403,
                    "y": 532.0881459612638
                },
                {
                    "x": 390.1340275471213,
                    "y": 534.0509035850777
                }
            ],
            "label": "trunk"
        },
        {
            "classIndex": 1,
            "layer": 0,
            "polygon": [
                {
                    "x": 809.653359677629,
                    "y": 511.5944198622124
                },
                {
                    "x": 812.9246223839855,
                    "y": 479.2907006369427
                },
                {
                    "x": 815.7869772520474,
                    "y": 432.67520707136356
                },
                {
                    "x": 812.515714545691,
                    "y": 407.7318289353958
                },
                {
                    "x": 827.2363967242948,
                    "y": 401.5982113609776
                },
                {
                    "x": 845.6372494475498,
                    "y": 404.869474067334
                },
                {
                    "x": 868.5360883920448,
                    "y": 417.9545248927597
                },
                {
                    "x": 846.455065124139,
                    "y": 446.5780735733784
                },
                {
                    "x": 843.592710256077,
                    "y": 534.902166645002
                },
                {
                    "x": 804.3375577798,
                    "y": 522.2260236578708
                }
            ],
            "label": "trunk"
        }
    ],
    "tags": [],
    "folder": "/a",
    "file": "68XYU5MDzePhXHI1muH_qg_-74.217122_40.544782_0_164.64.jpg",
    "lastEditDate": "2020-05-20T03:55:33.524Z",
    "firstEditDate": "2020-05-20T03:55:33.524Z"
}