{
    "_id": "ZgDKnW7eKWKjmtmj8",
    "url": "/%2Fa%2F8nKocpo0EVPU50mtzz1AQA_-74.233845_40.521279_0_276.35.jpg",
    "socName": "Cityscapes",
    "objects": [
        {
            "classIndex": 1,
            "layer": 0,
            "polygon": [
                {
                    "x": 405.2175515403613,
                    "y": 415.29622461978425
                },
                {
                    "x": 402.76410451059394,
                    "y": 391.98847783699466
                },
                {
                    "x": 423.2094964253216,
                    "y": 394.85083270505646
                },
                {
                    "x": 425.66294345508896,
                    "y": 413.25168542831153
                },
                {
                    "x": 421.16495723384884,
                    "y": 425.11001273885347
                },
                {
                    "x": 423.6184042636161,
                    "y": 503.2114098531132
                },
                {
                    "x": 428.1163904848562,
                    "y": 516.7053685168336
                },
                {
                    "x": 406.03536721695036,
                    "y": 517.9320920317173
                }
            ],
            "label": "trunk"
        }
    ],
    "tags": [],
    "folder": "/a",
    "file": "8nKocpo0EVPU50mtzz1AQA_-74.233845_40.521279_0_276.35.jpg",
    "lastEditDate": "2020-05-20T23:51:14.824Z",
    "firstEditDate": "2020-05-20T23:51:14.824Z"
}