{
    "_id": "dciEiq26TBzWDH9TL",
    "url": "/%2Fa%2F8R_y4QndfYcKHHUimkUTRQ_-74.203726_40.54275_0_255.48.jpg",
    "socName": "Cityscapes",
    "objects": [
        {
            "classIndex": 1,
            "layer": 0,
            "polygon": [
                {
                    "x": 441.8048199662031,
                    "y": 497.5477966982972
                },
                {
                    "x": 444.87162875341215,
                    "y": 448.98999090081895
                },
                {
                    "x": 457.64999870011695,
                    "y": 451.0345300922917
                },
                {
                    "x": 453.0497855193032,
                    "y": 507.25935785779285
                },
                {
                    "x": 457.1388639022489,
                    "y": 557.3505680488756
                },
                {
                    "x": 441.2936851683349,
                    "y": 557.8617028467438
                }
            ],
            "label": "trunk"
        },
        {
            "classIndex": 1,
            "layer": 0,
            "polygon": [
                {
                    "x": 783.0455988561033,
                    "y": 530.1474150526452
                },
                {
                    "x": 781.8188753412197,
                    "y": 469.62905498505137
                },
                {
                    "x": 799.8108202261801,
                    "y": 469.22014714675686
                },
                {
                    "x": 805.1266221240094,
                    "y": 539.55229533342
                },
                {
                    "x": 779.7743361497469,
                    "y": 544.8680972312493
                }
            ],
            "label": "trunk"
        }
    ],
    "tags": [],
    "folder": "/a",
    "file": "8R_y4QndfYcKHHUimkUTRQ_-74.203726_40.54275_0_255.48.jpg",
    "lastEditDate": "2020-05-20T22:56:17.674Z",
    "firstEditDate": "2020-05-20T22:56:17.674Z"
}